bigstore/__init__.py
bigstore/bigstore.py
bigstore/metadata.py
bigstore/backends/__init__.py
bigstore/backends/google.py
bigstore/backends/rackspace.py
bigstore/backends/s3.py
git_bigstore-2.0.2.data/scripts/git-bigstore
git_bigstore-2.0.2.dist-info/AUTHORS.md
git_bigstore-2.0.2.dist-info/LICENSE
git_bigstore-2.0.2.dist-info/METADATA
git_bigstore-2.0.2.dist-info/NOTICE
git_bigstore-2.0.2.dist-info/WHEEL
git_bigstore-2.0.2.dist-info/top_level.txt
git_bigstore-2.0.2.dist-info/RECORD
